memprofilerx/__init__.py
memprofilerx/reporter.py
memprofilerx/tracker.py
memprofilerx-0.1.0.dist-info/LICENSE
memprofilerx-0.1.0.dist-info/METADATA
memprofilerx-0.1.0.dist-info/WHEEL
memprofilerx-0.1.0.dist-info/RECORD
