Metadata-Version: 2.3
Name: memprofilerx
Version: 0.1.0
Summary: Advanced memory profiler for Python with live tracking and visual export.
License: MIT
Keywords: memory,profiling,performance,debugging,Python
Author: Nightz
Author-email: anonyzx15e@gmail.com
Requires-Python: >=3.12
Classifier: Programming Language :: Python :: 3
Classifier: License :: OSI Approved :: MIT License
Classifier: Operating System :: OS Independent
Classifier: Intended Audience :: Developers
Classifier: Topic :: System :: Monitoring
Requires-Dist: matplotlib (>=3.10.1,<4.0.0)
Requires-Dist: psutil (>=7.0.0,<8.0.0)
Requires-Dist: rich (>=14.0.0,<15.0.0)
